[
  {
    "field-name":"cvocDemo",
    "term-uri-field":"cvocDemoTermURI",
    "trigger-class":"test",
    "minChars": 1,
  "cvoc-url":"https://skosmos.dev.finto.fi/",
  "language":"en",
  "js-url":"/resources/js/cvoc-interface.js",
  "protocol": "skosmos",
  "retrieval-uri":"https://skosmos.dev.finto.fi/rest/v1/data?uri={0}",
  "vocab-uri" : "http://skos.um.es/unescothes/CS000",
  "term-parent-uri": "",
  "vocabs":["unesco","stw","agrovoc"],
  "managed-fields": {"vocabularyName":"cvocDemoVocabulary", "termName":"cvocDemoTerm", "vocabularyUri":"cvocDemoVocabularyURI"},
  "retrieval-filtering": {
          "termName": {"pattern": "{0}", "params":["/graph/uri=@id/prefLabel"]},
          "vocabularyName": {"pattern": "{0}", "params":["/graph/type=skos:ConceptScheme/prefLabel"]},
          "vocabularyUri": {"pattern": "{0}", "params":["/graph/type=skos:ConceptScheme/uri"]}
  }
},
{
          "field-name":"creator",
          "term-uri-field":"creator",
          "trigger-class":"person",
          "language":"en",
          "js-url":"/resources/js/people.js",
          "protocol": "orcid",
          "retrieval-uri":"https://pub.orcid.org/v3.0/{0}/person",
          "prefix":"https://orcid.org/",
          "vocabs":["orcid"],
          "managed-fields": {"personName":"authorName", "scheme": "authorIdentifierScheme", "@id":"authorIdentifier"},
          "retrieval-filtering": {
            "personName": {"pattern": "{0}, {1}", "params":["/name/family-name/value","/name/given-names/value"]},
            "@id": {"pattern": "{0}", "params":["@id"]},
            "scheme":{"pattern":"ORCID"}
          }
        },
{
        "field-name":"skosterm",
        "term-uri-field":"skosterm",
        "trigger-class":"unesco, stw, agrovac",
        "minChars": 1,
        "cvoc-url":"https://skosmos.dev.finto.fi/",
        "language":"en",
        "js-url":"/resources/js/skosmos.js",
        "protocol": "notskosmos",
        "retrieval-uri":"https://skosmos.dev.finto.fi/rest/v1/data?uri={0}",
        "vocabs":{
          "unesco": "http://skos.um.es/unescothes/CS000",
          "agrovoc" : "http://aims.fao.org/vest-registry/kos/agrovoc"
        },
        "managed-fields": {"vocabularyName":"cvocDemoVocabulary", "termName":"cvocDemoTerm", "vocabularyUri":"cvocDemoVocabularyURI"},
        "retrieval-filtering": {
          "@id": {"pattern": "{0}", "params":["@id"]},
          "termName": {"pattern": "{0}", "params":["/graph/uri=@id/prefLabel"]},
          "vocabularyName": {"pattern": "{0}", "params":["/graph/type=skos:ConceptScheme/prefLabel"]},
          "vocabularyUri": {"pattern": "{0}", "params":["/graph/type=skos:ConceptScheme/uri"]}
        }
}
]